04_tabla_SOP/tabla4SOP.v
module tabla4SOP();

  reg A, B, C, D;
  wire w1, w2, w3, w4, A1, A2, A3, A4, A5, A6, A7, OUTPUT;

  not NA(w1, A);
  not NB(w2, B);
  not NC(w3, C);
  not ND(w4, D);

  and U1(A1, w1, w2, w3, w4);
  and U2(A2, w1, w2, C, w4);
  and U3(A3, w1, w2, C, D);
  and U4(A4, w1, B, C, w4);
  and U5(A5, w1, B, C, D);
  and U6(A6, A, w2, w3, w4);
  and U7(A7, A, w2, C, w4);

  or U8(OUTPUT, A1, A2, A3, A4, A5, A6, A7);

  initial begin
    $display("A B C D | Y");
    $display("------------");
    $monitor("%b %b %b %b | %b", A, B, C, D, OUTPUT);

    A = 0; B = 0; C = 0; D = 0;
    #1 D = 1;
    #1 D = 0; C = 1;
    #1 D = 1;
    #1 D = 0; C = 0; B = 1;
    #1 D = 1;
    #1 D = 0; C = 1;
    #1 D = 1;
    #1 A = 1; B = 0; C = 0; D = 0;
    #1 D = 1;
    #1 C = 1; D = 0;
    #1 D = 1;
    #1 D = 0; C = 0; B = 1;
    #1 D = 1;
    #1 D = 0; C = 1;
    #1 D = 1;
    #1 $finish;

  end

  initial begin
      $dumpfile("tabla4SOP_tb.vcd");
      $dumpvars(0, tabla4SOP);
  end

endmodule

04_tabla_SOP/tabla4SOP_tb.vcd
$date
	Fri Jul 31 17:51:30 2020
$end
$version
	Icarus Verilog
$end
$timescale
	1ps
$end
$scope module tabla4SOP $end
$var wire 1 ! A1 $end
$var wire 1 " A2 $end
$var wire 1 # A3 $end
$var wire 1 $ A4 $end
$var wire 1 % A5 $end
$var wire 1 & A6 $end
$var wire 1 ' A7 $end
$var wire 1 ( OUTPUT $end
$var wire 1 ) w1 $end
$var wire 1 * w2 $end
$var wire 1 + w3 $end
$var wire 1 , w4 $end
$var reg 1 - A $end
$var reg 1 . B $end
$var reg 1 / C $end
$var reg 1 0 D $end
$upscope $end
$enddefinitions $end
#0
$dumpvars
00
0/
0.
0-
1,
1+
1*
1)
1(
0'
0&
0%
0$
0#
0"
1!
$end
#1
0(
0!
0,
10
#2
1(
1"
0+
1,
1/
00
#3
0"
1#
0,
10
#4
0(
0*
1+
0#
1,
1.
0/
00
#5
0,
10
#6
1(
1$
0+
1,
1/
00
#7
0$
1%
0,
10
#8
1&
1,
1+
0%
1*
0)
00
0/
0.
1-
#9
0(
0&
0,
10
#10
1(
1'
1,
0+
00
1/
#11
0(
0'
0,
10
#12
0*
1+
1,
1.
0/
00
#13
0,
10
#14
0+
1,
1/
00
#15
0,
10
