02_tabla_SOP/tabla2SOP.v
module tabla2SOP();

    reg  A, B, C;
    wire w1, w2, w3, A1, A2, A3, OUTPUT;

    not NA(w1, A);
    not NB(w2, B);
    not NC(w3, C);

    and U1(A1, w1, w2, C);
    and U2(A2, A, B, w3);
    and U3(A3, A, B, C);

    or U4(OUTPUT, A1, A2, A3);

    initial begin
        $display("A B C | Y");
        $display("----------");
        $monitor("%b %b %b | %b", A, B, C, OUTPUT);

        A = 0; B = 0; C=0;
        #1 C = 1;
        #1 B = 1; C = 0;
        #1 C = 1;
        #1 A = 1; B=0; C=0;
        #1 C = 1;
        #1 B = 1; C = 0;
        #1 C=1;
        #1 $finish;
    end

    /*initial begin
        $dumpfile("tabla2SOP_tb.vcd");
        $dumpvars(0, tabla2SOP);
    end*/

endmodule

02_tabla_SOP/tabla2SOP_tb.vcd
$date
	Fri Jul 31 17:48:36 2020
$end
$version
	Icarus Verilog
$end
$timescale
	1ps
$end
$scope module tabla2SOP $end
$var wire 1 ! A1 $end
$var wire 1 " A2 $end
$var wire 1 # A3 $end
$var wire 1 $ OUTPUT $end
$var wire 1 % w1 $end
$var wire 1 & w2 $end
$var wire 1 ' w3 $end
$var reg 1 ( A $end
$var reg 1 ) B $end
$var reg 1 * C $end
$upscope $end
$enddefinitions $end
#0
$dumpvars
0*
0)
0(
1'
1&
1%
0$
0#
0"
0!
$end
#1
1$
1!
0'
1*
#2
0$
0!
1'
0&
0*
1)
#3
0'
1*
#4
1'
1&
0%
0*
0)
1(
#5
0'
1*
#6
1$
1"
1'
0&
0*
1)
#7
0"
1#
0'
1*
