01_tabla_POS/tabla1POS.v
module tabla1POS();


  reg A, B, C;
  wire w1, w2, w3, O1, O2, O3, OUT;


  not NA(w1, A);
  not NB(w2, B);
  not NC(w3, C);
  or  U2(O1, A, B, w3);
  or  U3(O2, A, w2, w3);
  or  U4(O3, w1, w2, C);
  and U1(OUT, O1, O2, O3);

  initial begin
    $display("A B C Y");
    $monitor("%b %b %b %b", A, B, C, OUT);
    A = 0; B = 0; C=0;
    #1 C = 1;
    #1 B = 1; C = 0;
    #1 C = 1;
    #1 A = 1; B=0; C=0;
    #1 C = 1;
    #1 B = 1; C = 0;
    #1 C=1;
    #1 $finish;
  end

  initial
    begin
      $dumpfile("tabla1POS_tb.vcd");
      $dumpvars(0, tabla1POS);
    end
endmodule

01_tabla_POS/tabla1POS_tb.vcd
$date
	Thu Jul 30 13:32:04 2020
$end
$version
	Icarus Verilog
$end
$timescale
	1ps
$end
$scope module tabla1POS $end
$var wire 1 ! O1 $end
$var wire 1 " O2 $end
$var wire 1 # O3 $end
$var wire 1 $ OUT $end
$var wire 1 % w1 $end
$var wire 1 & w2 $end
$var wire 1 ' w3 $end
$var reg 1 ( A $end
$var reg 1 ) B $end
$var reg 1 * C $end
$upscope $end
$enddefinitions $end
#0
$dumpvars
0*
0)
0(
1'
1&
1%
1$
1#
1"
1!
$end
#1
0$
0!
0'
1*
#2
1$
1'
1!
0&
0*
1)
#3
0$
0"
0'
1*
#4
1$
1'
1&
1"
0%
0*
0)
1(
#5
0'
1*
#6
0$
0#
1'
0&
0*
1)
#7
1$
1#
0'
1*
