02_tabla_POS/tabla2POS.v
module tabla2POS();

    reg  A, B, C;
    wire w1, w2, w3, O1, O2, O3, O4, O5, OUTPUT;

    not NA(w1, A);
    not NB(w2, B);
    not NC(w3, C);

    or  U1(O1, A, B, C);
    or  U2(O2, A, w2, C);
    or  U3(O3, A, w2, w3);
    or  U4(O4, w1, B, C);
    or  U5(O5, w1, B, w3);

    and U6(OUTPUT, O1, O2, O3, O4, O5);

    initial begin
        $display("A B C | Y");
        $display("----------");
        $monitor("%b %b %b | %b", A, B, C, OUTPUT);

        A = 0; B = 0; C=0;
        #1 C = 1;
        #1 B = 1; C = 0;
        #1 C = 1;
        #1 A = 1; B=0; C=0;
        #1 C = 1;
        #1 B = 1; C = 0;
        #1 C=1;
        #1 $finish;
    end

    initial begin
        $dumpfile("tabla2POS_tb.vcd");
        $dumpvars(0, tabla2POS);
    end

endmodule

02_tabla_POS/tabla2POS_tb.vcd
$date
	Fri Jul 31 17:49:41 2020
$end
$version
	Icarus Verilog
$end
$timescale
	1ps
$end
$scope module tabla2POS $end
$var wire 1 ! O1 $end
$var wire 1 " O2 $end
$var wire 1 # O3 $end
$var wire 1 $ O4 $end
$var wire 1 % O5 $end
$var wire 1 & OUTPUT $end
$var wire 1 ' w1 $end
$var wire 1 ( w2 $end
$var wire 1 ) w3 $end
$var reg 1 * A $end
$var reg 1 + B $end
$var reg 1 , C $end
$upscope $end
$enddefinitions $end
#0
$dumpvars
0,
0+
0*
1)
1(
1'
0&
1%
1$
1#
1"
0!
$end
#1
1&
1!
0)
1,
#2
0&
0"
1)
0(
0,
1+
#3
0#
1"
0)
1,
#4
1)
1%
0$
1(
1#
0'
0,
0+
1*
#5
0%
1$
0)
1,
#6
1&
1)
1%
0(
0,
1+
#7
0)
1,
