04_tabla_POS/tabla4POS.v
module tabla4POS();

  reg A, B, C, D;
  wire w1, w2, w3, w4, O1, O2, O3, O4, O5, O6, O7, O8, O9, OUTPUT;

  not NA(w1, A);
  not NB(w2, B);
  not NC(w3, C);
  not ND(w4, D);

  or U1(O1, A, B, C, w4);
  or U2(O2, A, w2, C, D);
  or U3(O3, A, w2, C, w4);
  or U4(O4, w1, B, C, w4);
  or U5(O5, w1, B, w3, w4);
  or U6(O6, w1, w2, C, D);
  or U7(O7, w1, w2, C, w4);
  or U8(O8, w1, w2, w3, D);
  or U9(O9, w1, w2, w3, w4);

  and U10(OUTPUT, O1, O2, O3, O4, O5, O6, O7, O8, O9);

  initial begin
    $display("A B C D | Y");
    $display("------------");
    $monitor("%b %b %b %b | %b", A, B, C, D, OUTPUT);

    A = 0; B = 0; C = 0; D = 0;
    #1 D = 1;
    #1 D = 0; C = 1;
    #1 D = 1;
    #1 D = 0; C = 0; B = 1;
    #1 D = 1;
    #1 D = 0; C = 1;
    #1 D = 1;
    #1 A = 1; B = 0; C = 0; D = 0;
    #1 D = 1;
    #1 C = 1; D = 0;
    #1 D = 1;
    #1 D = 0; C = 0; B = 1;
    #1 D = 1;
    #1 D = 0; C = 1;
    #1 D = 1;
    #1 $finish;

  end

  /*initial begin
      $dumpfile("tabla4POS_tb.vcd");
      $dumpvars(0, tabla4POS);
  end*/

endmodule

04_tabla_POS/tabla4POS_tb.vcd
$date
	Fri Jul 31 17:51:48 2020
$end
$version
	Icarus Verilog
$end
$timescale
	1ps
$end
$scope module tabla4POS $end
$var wire 1 ! O1 $end
$var wire 1 " O2 $end
$var wire 1 # O3 $end
$var wire 1 $ O4 $end
$var wire 1 % O5 $end
$var wire 1 & O6 $end
$var wire 1 ' O7 $end
$var wire 1 ( O8 $end
$var wire 1 ) O9 $end
$var wire 1 * OUTPUT $end
$var wire 1 + w1 $end
$var wire 1 , w2 $end
$var wire 1 - w3 $end
$var wire 1 . w4 $end
$var reg 1 / A $end
$var reg 1 0 B $end
$var reg 1 1 C $end
$var reg 1 2 D $end
$upscope $end
$enddefinitions $end
#0
$dumpvars
02
01
00
0/
1.
1-
1,
1+
1*
1)
1(
1'
1&
1%
1$
1#
1"
1!
$end
#1
0*
0!
0.
12
#2
1*
1!
0-
1.
11
02
#3
0.
12
#4
0*
0"
0,
1-
1.
10
01
02
#5
0#
1"
0.
12
#6
1*
1#
0-
1.
11
02
#7
0.
12
#8
1*
1.
1-
1%
1$
1,
0+
02
01
00
1/
#9
0*
0$
0.
12
#10
1*
1.
1$
0-
02
11
#11
0*
0%
0.
12
#12
0&
1%
0,
1-
1.
10
01
02
#13
0'
1&
0.
12
#14
0(
1'
0-
1.
11
02
#15
0)
1(
0.
12
