01_tabla_SOP/tabla1SOP.v
module tabla1SOP();

    reg  A, B, C;
    wire w1, w2, w3, A1, A2, A3, A4, A5, OUTPUT;

    not NA(w1, A);
    not NB(w2, B);
    not NC(w3, C);

    and U1(A1, w1, w2, w3);
    and U2(A2, w1, B, w3);
    and U3(A3, A, w2, w3);
    and U4(A4, A, w2, C);
    and U5(A5, A, B, C);

    or U6(OUTPUT, A1, A2, A3, A4, A5);

    initial begin
        $display("A B C | Y");
        $display("----------");
        $monitor("%b %b %b | %b", A, B, C, OUTPUT);

        A = 0; B = 0; C=0;
        #1 C = 1;
        #1 B = 1; C = 0;
        #1 C = 1;
        #1 A = 1; B=0; C=0;
        #1 C = 1;
        #1 B = 1; C = 0;
        #1 C=1;
        #1 $finish;
    end

    initial begin
        $dumpfile("tabla1SOP_tb.vcd");
        $dumpvars(0, tabla1SOP);
    end

endmodule

01_tabla_SOP/tabla1SOP_tb.vcd
$date
	Fri Jul 31 17:49:15 2020
$end
$version
	Icarus Verilog
$end
$timescale
	1ps
$end
$scope module tabla1SOP $end
$var wire 1 ! A1 $end
$var wire 1 " A2 $end
$var wire 1 # A3 $end
$var wire 1 $ A4 $end
$var wire 1 % A5 $end
$var wire 1 & OUTPUT $end
$var wire 1 ' w1 $end
$var wire 1 ( w2 $end
$var wire 1 ) w3 $end
$var reg 1 * A $end
$var reg 1 + B $end
$var reg 1 , C $end
$upscope $end
$enddefinitions $end
#0
$dumpvars
0,
0+
0*
1)
1(
1'
1&
0%
0$
0#
0"
1!
$end
#1
0&
0!
0)
1,
#2
1&
1"
1)
0(
0,
1+
#3
0&
0"
0)
1,
#4
1&
1#
1)
1(
0'
0,
0+
1*
#5
0#
1$
0)
1,
#6
0&
0$
1)
0(
0,
1+
#7
1&
1%
0)
1,
